pyfun_my/__init__.py
pyfun_my/option.py
pyfun_my/pyfunList.py
pyfun_my-0.0.1.dist-info/METADATA
pyfun_my-0.0.1.dist-info/WHEEL
pyfun_my-0.0.1.dist-info/licenses/LICENSE
pyfun_my-0.0.1.dist-info/RECORD
