Metadata-Version: 2.3
Name: pyfun_my
Version: 0.0.1
Summary: A small example package
Project-URL: Homepage, https://github.com/mywyau/pyfun
Project-URL: Issues, https://github.com/mywyau/pyfun/issues
Author-email: Michael Yau <m.yw.yau@gmail.com>
License-File: LICENSE
Classifier: License :: OSI Approved :: MIT License
Classifier: Operating System :: OS Independent
Classifier: Programming Language :: Python :: 3
Requires-Python: >=3.8
